<?xml version='1.0'?>
<ns2:test-suite xmlns:ns2='urn:model.allure.qatools.yandex.ru' start='1653293642735' stop='1653293649012'>
    <name>Products API tests: List All Products List all products</name>
    <title>Products API tests: List All Products List all products</title>
    <test-cases>
        <test-case start='1653293642736' status='passed' stop='1653293642873'>
            <name>defaults</name>
            <title>defaults</title>
            <labels/>
            <parameters/>
            <steps/>
            <attachments/>
        </test-case>
        <test-case start='1653293642873' status='passed' stop='1653293643373'>
            <name>pagination</name>
            <title>pagination</title>
            <labels/>
            <parameters/>
            <steps/>
            <attachments/>
        </test-case>
        <test-case start='1653293643373' status='passed' stop='1653293643576'>
            <name>search</name>
            <title>search</title>
            <labels/>
            <parameters/>
            <steps/>
            <attachments/>
        </test-case>
        <test-case start='1653293643576' status='passed' stop='1653293644188'>
            <name>inclusion / exclusion</name>
            <title>inclusion / exclusion</title>
            <labels/>
            <parameters/>
            <steps/>
            <attachments/>
        </test-case>
        <test-case start='1653293644188' status='passed' stop='1653293644519'>
            <name>slug</name>
            <title>slug</title>
            <labels/>
            <parameters/>
            <steps/>
            <attachments/>
        </test-case>
        <test-case start='1653293644519' status='passed' stop='1653293644675'>
            <name>sku</name>
            <title>sku</title>
            <labels/>
            <parameters/>
            <steps/>
            <attachments/>
        </test-case>
        <test-case start='1653293644675' status='passed' stop='1653293645046'>
            <name>type</name>
            <title>type</title>
            <labels/>
            <parameters/>
            <steps/>
            <attachments/>
        </test-case>
        <test-case start='1653293645046' status='passed' stop='1653293645262'>
            <name>featured</name>
            <title>featured</title>
            <labels/>
            <parameters/>
            <steps/>
            <attachments/>
        </test-case>
        <test-case start='1653293645262' status='passed' stop='1653293645483'>
            <name>categories</name>
            <title>categories</title>
            <labels/>
            <parameters/>
            <steps/>
            <attachments/>
        </test-case>
        <test-case start='1653293645483' status='passed' stop='1653293645736'>
            <name>on sale</name>
            <title>on sale</title>
            <labels/>
            <parameters/>
            <steps/>
            <attachments/>
        </test-case>
        <test-case start='1653293645736' status='passed' stop='1653293646142'>
            <name>price</name>
            <title>price</title>
            <labels/>
            <parameters/>
            <steps/>
            <attachments/>
        </test-case>
        <test-case start='1653293646142' status='passed' stop='1653293646397'>
            <name>before / after</name>
            <title>before / after</title>
            <labels/>
            <parameters/>
            <steps/>
            <attachments/>
        </test-case>
        <test-case start='1653293646397' status='passed' stop='1653293646491'>
            <name>attributes</name>
            <title>attributes</title>
            <labels/>
            <parameters/>
            <steps/>
            <attachments/>
        </test-case>
        <test-case start='1653293646491' status='passed' stop='1653293646636'>
            <name>status</name>
            <title>status</title>
            <labels/>
            <parameters/>
            <steps/>
            <attachments/>
        </test-case>
        <test-case start='1653293646636' status='passed' stop='1653293646716'>
            <name>shipping class</name>
            <title>shipping class</title>
            <labels/>
            <parameters/>
            <steps/>
            <attachments/>
        </test-case>
        <test-case start='1653293646716' status='passed' stop='1653293646795'>
            <name>tax class</name>
            <title>tax class</title>
            <labels/>
            <parameters/>
            <steps/>
            <attachments/>
        </test-case>
        <test-case start='1653293646795' status='passed' stop='1653293646874'>
            <name>stock status</name>
            <title>stock status</title>
            <labels/>
            <parameters/>
            <steps/>
            <attachments/>
        </test-case>
        <test-case start='1653293646874' status='passed' stop='1653293646960'>
            <name>tags</name>
            <title>tags</title>
            <labels/>
            <parameters/>
            <steps/>
            <attachments/>
        </test-case>
        <test-case start='1653293646960' status='passed' stop='1653293647165'>
            <name>parent</name>
            <title>parent</title>
            <labels/>
            <parameters/>
            <steps/>
            <attachments/>
        </test-case>
    </test-cases>
</ns2:test-suite>