<?xml version='1.0'?>
<ns2:test-suite xmlns:ns2='urn:model.allure.qatools.yandex.ru' start='1653371899500' stop='1653371901109'>
    <name>Products API tests: List All Products List all products orderby</name>
    <title>Products API tests: List All Products List all products orderby</title>
    <test-cases>
        <test-case start='1653371899500' status='passed' stop='1653371899611'>
            <name>default</name>
            <title>default</title>
            <labels/>
            <parameters/>
            <steps/>
            <attachments/>
        </test-case>
        <test-case start='1653371899612' status='passed' stop='1653371899716'>
            <name>date</name>
            <title>date</title>
            <labels/>
            <parameters/>
            <steps/>
            <attachments/>
        </test-case>
        <test-case start='1653371899716' status='passed' stop='1653371899946'>
            <name>id</name>
            <title>id</title>
            <labels/>
            <parameters/>
            <steps/>
            <attachments/>
        </test-case>
        <test-case start='1653371899947' status='passed' stop='1653371900233'>
            <name>title</name>
            <title>title</title>
            <labels/>
            <parameters/>
            <steps/>
            <attachments/>
        </test-case>
        <test-case start='1653371900233' status='passed' stop='1653371900492'>
            <name>slug</name>
            <title>slug</title>
            <labels/>
            <parameters/>
            <steps/>
            <attachments/>
        </test-case>
        <test-case start='1653371900492' status='passed' stop='1653371900752'>
            <name>price</name>
            <title>price</title>
            <labels/>
            <parameters/>
            <steps/>
            <attachments/>
        </test-case>
        <test-case start='1653371900752' status='passed' stop='1653371900944'>
            <name>include</name>
            <title>include</title>
            <labels/>
            <parameters/>
            <steps/>
            <attachments/>
        </test-case>
        <test-case start='1653371900945' status='passed' stop='1653371901027'>
            <name>rating (desc)</name>
            <title>rating (desc)</title>
            <labels/>
            <parameters/>
            <steps/>
            <attachments/>
        </test-case>
        <test-case start='1653371901027' status='pending' stop='1653371901027'>
            <name>rating (asc)</name>
            <title>rating (asc)</title>
            <labels/>
            <parameters/>
            <steps/>
            <attachments/>
            <failure>
                <message>Temporarily disabled with xit</message>
                <stack-trace>undefined</stack-trace>
            </failure>
        </test-case>
        <test-case start='1653371901027' status='passed' stop='1653371901109'>
            <name>popularity (desc)</name>
            <title>popularity (desc)</title>
            <labels/>
            <parameters/>
            <steps/>
            <attachments/>
        </test-case>
        <test-case start='1653371901109' status='pending' stop='1653371901109'>
            <name>popularity (asc)</name>
            <title>popularity (asc)</title>
            <labels/>
            <parameters/>
            <steps/>
            <attachments/>
            <failure>
                <message>Temporarily disabled with xit</message>
                <stack-trace>undefined</stack-trace>
            </failure>
        </test-case>
    </test-cases>
</ns2:test-suite>