<?xml version='1.0'?>
<ns2:test-suite xmlns:ns2='urn:model.allure.qatools.yandex.ru' start='1652863737649' stop='1652863737923'>
    <name>Orders API tests: CRUD Create an order</name>
    <title>Orders API tests: CRUD Create an order</title>
    <test-cases>
        <test-case start='1652863737650' status='failed' stop='1652863737693'>
            <name>can create a pending order by default</name>
            <title>can create a pending order by default</title>
            <labels/>
            <parameters/>
            <steps/>
            <attachments/>
            <failure>
                <message>Error: expect(received).toEqual(expected) // deep equality
                
                Expected: 201
                Received: 404</message>
                <stack-trace>Error: expect(received).toEqual(expected) // deep equality
                
                Expected: 201
                Received: 404
                    at Object.&lt;anonymous> (/home/runner/work/woocommerce/woocommerce/packages/js/api-core-tests/tests/orders/orders-crud.test.js:82:21)
                    at processTicksAndRejections (node:internal/process/task_queues:96:5)</stack-trace>
            </failure>
        </test-case>
        <test-case start='1652863737693' status='failed' stop='1652863737726'>
            <name>can create an order with status 'pending'</name>
            <title>can create an order with status 'pending'</title>
            <labels/>
            <parameters/>
            <steps/>
            <attachments/>
            <failure>
                <message>Error: expect(received).toEqual(expected) // deep equality
                
                Expected: 201
                Received: 404</message>
                <stack-trace>Error: expect(received).toEqual(expected) // deep equality
                
                Expected: 201
                Received: 404
                    at /home/runner/work/woocommerce/woocommerce/packages/js/api-core-tests/tests/orders/orders-crud.test.js:98:22
                    at processTicksAndRejections (node:internal/process/task_queues:96:5)</stack-trace>
            </failure>
        </test-case>
        <test-case start='1652863737726' status='failed' stop='1652863737758'>
            <name>can create an order with status 'processing'</name>
            <title>can create an order with status 'processing'</title>
            <labels/>
            <parameters/>
            <steps/>
            <attachments/>
            <failure>
                <message>Error: expect(received).toEqual(expected) // deep equality
                
                Expected: 201
                Received: 404</message>
                <stack-trace>Error: expect(received).toEqual(expected) // deep equality
                
                Expected: 201
                Received: 404
                    at /home/runner/work/woocommerce/woocommerce/packages/js/api-core-tests/tests/orders/orders-crud.test.js:98:22
                    at processTicksAndRejections (node:internal/process/task_queues:96:5)</stack-trace>
            </failure>
        </test-case>
        <test-case start='1652863737759' status='failed' stop='1652863737791'>
            <name>can create an order with status 'on-hold'</name>
            <title>can create an order with status 'on-hold'</title>
            <labels/>
            <parameters/>
            <steps/>
            <attachments/>
            <failure>
                <message>Error: expect(received).toEqual(expected) // deep equality
                
                Expected: 201
                Received: 404</message>
                <stack-trace>Error: expect(received).toEqual(expected) // deep equality
                
                Expected: 201
                Received: 404
                    at /home/runner/work/woocommerce/woocommerce/packages/js/api-core-tests/tests/orders/orders-crud.test.js:98:22
                    at processTicksAndRejections (node:internal/process/task_queues:96:5)</stack-trace>
            </failure>
        </test-case>
        <test-case start='1652863737791' status='failed' stop='1652863737824'>
            <name>can create an order with status 'completed'</name>
            <title>can create an order with status 'completed'</title>
            <labels/>
            <parameters/>
            <steps/>
            <attachments/>
            <failure>
                <message>Error: expect(received).toEqual(expected) // deep equality
                
                Expected: 201
                Received: 404</message>
                <stack-trace>Error: expect(received).toEqual(expected) // deep equality
                
                Expected: 201
                Received: 404
                    at /home/runner/work/woocommerce/woocommerce/packages/js/api-core-tests/tests/orders/orders-crud.test.js:98:22
                    at processTicksAndRejections (node:internal/process/task_queues:96:5)</stack-trace>
            </failure>
        </test-case>
        <test-case start='1652863737824' status='failed' stop='1652863737857'>
            <name>can create an order with status 'cancelled'</name>
            <title>can create an order with status 'cancelled'</title>
            <labels/>
            <parameters/>
            <steps/>
            <attachments/>
            <failure>
                <message>Error: expect(received).toEqual(expected) // deep equality
                
                Expected: 201
                Received: 404</message>
                <stack-trace>Error: expect(received).toEqual(expected) // deep equality
                
                Expected: 201
                Received: 404
                    at /home/runner/work/woocommerce/woocommerce/packages/js/api-core-tests/tests/orders/orders-crud.test.js:98:22
                    at processTicksAndRejections (node:internal/process/task_queues:96:5)</stack-trace>
            </failure>
        </test-case>
        <test-case start='1652863737857' status='failed' stop='1652863737889'>
            <name>can create an order with status 'refunded'</name>
            <title>can create an order with status 'refunded'</title>
            <labels/>
            <parameters/>
            <steps/>
            <attachments/>
            <failure>
                <message>Error: expect(received).toEqual(expected) // deep equality
                
                Expected: 201
                Received: 404</message>
                <stack-trace>Error: expect(received).toEqual(expected) // deep equality
                
                Expected: 201
                Received: 404
                    at /home/runner/work/woocommerce/woocommerce/packages/js/api-core-tests/tests/orders/orders-crud.test.js:98:22
                    at processTicksAndRejections (node:internal/process/task_queues:96:5)</stack-trace>
            </failure>
        </test-case>
        <test-case start='1652863737889' status='failed' stop='1652863737922'>
            <name>can create an order with status 'failed'</name>
            <title>can create an order with status 'failed'</title>
            <labels/>
            <parameters/>
            <steps/>
            <attachments/>
            <failure>
                <message>Error: expect(received).toEqual(expected) // deep equality
                
                Expected: 201
                Received: 404</message>
                <stack-trace>Error: expect(received).toEqual(expected) // deep equality
                
                Expected: 201
                Received: 404
                    at /home/runner/work/woocommerce/woocommerce/packages/js/api-core-tests/tests/orders/orders-crud.test.js:98:22
                    at processTicksAndRejections (node:internal/process/task_queues:96:5)</stack-trace>
            </failure>
        </test-case>
    </test-cases>
</ns2:test-suite>