<?xml version='1.0'?>
<ns2:test-suite xmlns:ns2='urn:model.allure.qatools.yandex.ru' start='1653660263974' stop='1653660265511'>
    <name>Products API tests: List All Products List all products orderby</name>
    <title>Products API tests: List All Products List all products orderby</title>
    <test-cases>
        <test-case start='1653660263974' status='passed' stop='1653660264085'>
            <name>default</name>
            <title>default</title>
            <labels/>
            <parameters/>
            <steps/>
            <attachments/>
        </test-case>
        <test-case start='1653660264085' status='passed' stop='1653660264183'>
            <name>date</name>
            <title>date</title>
            <labels/>
            <parameters/>
            <steps/>
            <attachments/>
        </test-case>
        <test-case start='1653660264183' status='passed' stop='1653660264385'>
            <name>id</name>
            <title>id</title>
            <labels/>
            <parameters/>
            <steps/>
            <attachments/>
        </test-case>
        <test-case start='1653660264385' status='passed' stop='1653660264630'>
            <name>title</name>
            <title>title</title>
            <labels/>
            <parameters/>
            <steps/>
            <attachments/>
        </test-case>
        <test-case start='1653660264630' status='passed' stop='1653660264902'>
            <name>slug</name>
            <title>slug</title>
            <labels/>
            <parameters/>
            <steps/>
            <attachments/>
        </test-case>
        <test-case start='1653660264902' status='passed' stop='1653660265168'>
            <name>price</name>
            <title>price</title>
            <labels/>
            <parameters/>
            <steps/>
            <attachments/>
        </test-case>
        <test-case start='1653660265168' status='passed' stop='1653660265352'>
            <name>include</name>
            <title>include</title>
            <labels/>
            <parameters/>
            <steps/>
            <attachments/>
        </test-case>
        <test-case start='1653660265352' status='passed' stop='1653660265431'>
            <name>rating (desc)</name>
            <title>rating (desc)</title>
            <labels/>
            <parameters/>
            <steps/>
            <attachments/>
        </test-case>
        <test-case start='1653660265431' status='pending' stop='1653660265431'>
            <name>rating (asc)</name>
            <title>rating (asc)</title>
            <labels/>
            <parameters/>
            <steps/>
            <attachments/>
            <failure>
                <message>Temporarily disabled with xit</message>
                <stack-trace>undefined</stack-trace>
            </failure>
        </test-case>
        <test-case start='1653660265431' status='passed' stop='1653660265511'>
            <name>popularity (desc)</name>
            <title>popularity (desc)</title>
            <labels/>
            <parameters/>
            <steps/>
            <attachments/>
        </test-case>
        <test-case start='1653660265511' status='pending' stop='1653660265511'>
            <name>popularity (asc)</name>
            <title>popularity (asc)</title>
            <labels/>
            <parameters/>
            <steps/>
            <attachments/>
            <failure>
                <message>Temporarily disabled with xit</message>
                <stack-trace>undefined</stack-trace>
            </failure>
        </test-case>
    </test-cases>
</ns2:test-suite>