<?xml version='1.0'?>
<ns2:test-suite xmlns:ns2='urn:model.allure.qatools.yandex.ru' start='1656057810762' stop='1656057818792'>
    <name>Products API tests: List All Products List all products</name>
    <title>Products API tests: List All Products List all products</title>
    <test-cases>
        <test-case start='1656057810763' status='passed' stop='1656057810965'>
            <name>defaults</name>
            <title>defaults</title>
            <labels/>
            <parameters/>
            <steps/>
            <attachments/>
        </test-case>
        <test-case start='1656057810965' status='passed' stop='1656057811627'>
            <name>pagination</name>
            <title>pagination</title>
            <labels/>
            <parameters/>
            <steps/>
            <attachments/>
        </test-case>
        <test-case start='1656057811627' status='passed' stop='1656057811879'>
            <name>search</name>
            <title>search</title>
            <labels/>
            <parameters/>
            <steps/>
            <attachments/>
        </test-case>
        <test-case start='1656057811879' status='passed' stop='1656057812441'>
            <name>inclusion / exclusion</name>
            <title>inclusion / exclusion</title>
            <labels/>
            <parameters/>
            <steps/>
            <attachments/>
        </test-case>
        <test-case start='1656057812441' status='passed' stop='1656057812678'>
            <name>slug</name>
            <title>slug</title>
            <labels/>
            <parameters/>
            <steps/>
            <attachments/>
        </test-case>
        <test-case start='1656057812678' status='passed' stop='1656057812918'>
            <name>sku</name>
            <title>sku</title>
            <labels/>
            <parameters/>
            <steps/>
            <attachments/>
        </test-case>
        <test-case start='1656057812918' status='passed' stop='1656057813443'>
            <name>type</name>
            <title>type</title>
            <labels/>
            <parameters/>
            <steps/>
            <attachments/>
        </test-case>
        <test-case start='1656057813443' status='passed' stop='1656057813752'>
            <name>featured</name>
            <title>featured</title>
            <labels/>
            <parameters/>
            <steps/>
            <attachments/>
        </test-case>
        <test-case start='1656057813752' status='passed' stop='1656057814090'>
            <name>categories</name>
            <title>categories</title>
            <labels/>
            <parameters/>
            <steps/>
            <attachments/>
        </test-case>
        <test-case start='1656057814090' status='passed' stop='1656057814434'>
            <name>on sale</name>
            <title>on sale</title>
            <labels/>
            <parameters/>
            <steps/>
            <attachments/>
        </test-case>
        <test-case start='1656057814435' status='passed' stop='1656057814850'>
            <name>price</name>
            <title>price</title>
            <labels/>
            <parameters/>
            <steps/>
            <attachments/>
        </test-case>
        <test-case start='1656057814850' status='passed' stop='1656057815121'>
            <name>before / after</name>
            <title>before / after</title>
            <labels/>
            <parameters/>
            <steps/>
            <attachments/>
        </test-case>
        <test-case start='1656057815121' status='passed' stop='1656057815278'>
            <name>attributes</name>
            <title>attributes</title>
            <labels/>
            <parameters/>
            <steps/>
            <attachments/>
        </test-case>
        <test-case start='1656057815279' status='passed' stop='1656057815510'>
            <name>status</name>
            <title>status</title>
            <labels/>
            <parameters/>
            <steps/>
            <attachments/>
        </test-case>
        <test-case start='1656057815510' status='passed' stop='1656057815624'>
            <name>shipping class</name>
            <title>shipping class</title>
            <labels/>
            <parameters/>
            <steps/>
            <attachments/>
        </test-case>
        <test-case start='1656057815624' status='passed' stop='1656057815736'>
            <name>tax class</name>
            <title>tax class</title>
            <labels/>
            <parameters/>
            <steps/>
            <attachments/>
        </test-case>
        <test-case start='1656057815736' status='passed' stop='1656057815860'>
            <name>stock status</name>
            <title>stock status</title>
            <labels/>
            <parameters/>
            <steps/>
            <attachments/>
        </test-case>
        <test-case start='1656057815860' status='passed' stop='1656057815990'>
            <name>tags</name>
            <title>tags</title>
            <labels/>
            <parameters/>
            <steps/>
            <attachments/>
        </test-case>
        <test-case start='1656057815990' status='passed' stop='1656057816286'>
            <name>parent</name>
            <title>parent</title>
            <labels/>
            <parameters/>
            <steps/>
            <attachments/>
        </test-case>
    </test-cases>
</ns2:test-suite>