<?xml version='1.0'?>
<ns2:test-suite xmlns:ns2='urn:model.allure.qatools.yandex.ru' start='1655716459868' stop='1655716462440'>
    <name>Order Search API tests</name>
    <title>Order Search API tests</title>
    <test-cases>
        <test-case start='1655716460216' status='passed' stop='1655716460394'>
            <name>can search by orderId</name>
            <title>can search by orderId</title>
            <labels/>
            <parameters/>
            <steps/>
            <attachments/>
        </test-case>
        <test-case start='1655716460394' status='passed' stop='1655716460523'>
            <name>can search by billing first name</name>
            <title>can search by billing first name</title>
            <labels/>
            <parameters/>
            <steps/>
            <attachments/>
        </test-case>
        <test-case start='1655716460523' status='passed' stop='1655716460648'>
            <name>can search by billing company name</name>
            <title>can search by billing company name</title>
            <labels/>
            <parameters/>
            <steps/>
            <attachments/>
        </test-case>
        <test-case start='1655716460648' status='passed' stop='1655716460771'>
            <name>can search by billing address 2</name>
            <title>can search by billing address 2</title>
            <labels/>
            <parameters/>
            <steps/>
            <attachments/>
        </test-case>
        <test-case start='1655716460772' status='passed' stop='1655716460898'>
            <name>can search by billing city name</name>
            <title>can search by billing city name</title>
            <labels/>
            <parameters/>
            <steps/>
            <attachments/>
        </test-case>
        <test-case start='1655716460898' status='passed' stop='1655716461034'>
            <name>can search by billing post code</name>
            <title>can search by billing post code</title>
            <labels/>
            <parameters/>
            <steps/>
            <attachments/>
        </test-case>
        <test-case start='1655716461034' status='passed' stop='1655716461170'>
            <name>can search by billing phone</name>
            <title>can search by billing phone</title>
            <labels/>
            <parameters/>
            <steps/>
            <attachments/>
        </test-case>
        <test-case start='1655716461170' status='passed' stop='1655716461319'>
            <name>can search by billing state</name>
            <title>can search by billing state</title>
            <labels/>
            <parameters/>
            <steps/>
            <attachments/>
        </test-case>
        <test-case start='1655716461319' status='passed' stop='1655716461447'>
            <name>can search by shipping first name</name>
            <title>can search by shipping first name</title>
            <labels/>
            <parameters/>
            <steps/>
            <attachments/>
        </test-case>
        <test-case start='1655716461447' status='passed' stop='1655716461580'>
            <name>can search by shipping last name</name>
            <title>can search by shipping last name</title>
            <labels/>
            <parameters/>
            <steps/>
            <attachments/>
        </test-case>
        <test-case start='1655716461580' status='passed' stop='1655716461715'>
            <name>can search by shipping address 2</name>
            <title>can search by shipping address 2</title>
            <labels/>
            <parameters/>
            <steps/>
            <attachments/>
        </test-case>
        <test-case start='1655716461715' status='passed' stop='1655716461843'>
            <name>can search by shipping city</name>
            <title>can search by shipping city</title>
            <labels/>
            <parameters/>
            <steps/>
            <attachments/>
        </test-case>
        <test-case start='1655716461844' status='passed' stop='1655716461971'>
            <name>can search by shipping post code</name>
            <title>can search by shipping post code</title>
            <labels/>
            <parameters/>
            <steps/>
            <attachments/>
        </test-case>
        <test-case start='1655716461971' status='passed' stop='1655716462103'>
            <name>can search by shipping state</name>
            <title>can search by shipping state</title>
            <labels/>
            <parameters/>
            <steps/>
            <attachments/>
        </test-case>
        <test-case start='1655716462103' status='passed' stop='1655716462236'>
            <name>can return an empty result set when no matches were found</name>
            <title>can return an empty result set when no matches were found</title>
            <labels/>
            <parameters/>
            <steps/>
            <attachments/>
        </test-case>
    </test-cases>
</ns2:test-suite>