<?xml version='1.0'?>
<ns2:test-suite xmlns:ns2='urn:model.allure.qatools.yandex.ru' start='1653043123283' stop='1653043123839'>
    <name>Coupons API tests List coupons</name>
    <title>Coupons API tests List coupons</title>
    <test-cases>
        <test-case start='1653043123409' status='passed' stop='1653043123491'>
            <name>can list all coupons by default</name>
            <title>can list all coupons by default</title>
            <labels/>
            <parameters/>
            <steps/>
            <attachments/>
        </test-case>
        <test-case start='1653043123491' status='passed' stop='1653043123570'>
            <name>can limit result set to matching code</name>
            <title>can limit result set to matching code</title>
            <labels/>
            <parameters/>
            <steps/>
            <attachments/>
        </test-case>
        <test-case start='1653043123570' status='passed' stop='1653043123652'>
            <name>can paginate results</name>
            <title>can paginate results</title>
            <labels/>
            <parameters/>
            <steps/>
            <attachments/>
        </test-case>
        <test-case start='1653043123652' status='passed' stop='1653043123736'>
            <name>can limit results to matching string</name>
            <title>can limit results to matching string</title>
            <labels/>
            <parameters/>
            <steps/>
            <attachments/>
        </test-case>
    </test-cases>
</ns2:test-suite>