<?xml version='1.0'?>
<ns2:test-suite xmlns:ns2='urn:model.allure.qatools.yandex.ru' start='1654056730410' stop='1654056731876'>
    <name>Order Search API tests</name>
    <title>Order Search API tests</title>
    <test-cases>
        <test-case start='1654056730600' status='passed' stop='1654056730677'>
            <name>can search by orderId</name>
            <title>can search by orderId</title>
            <labels/>
            <parameters/>
            <steps/>
            <attachments/>
        </test-case>
        <test-case start='1654056730678' status='passed' stop='1654056730752'>
            <name>can search by billing first name</name>
            <title>can search by billing first name</title>
            <labels/>
            <parameters/>
            <steps/>
            <attachments/>
        </test-case>
        <test-case start='1654056730752' status='passed' stop='1654056730839'>
            <name>can search by billing company name</name>
            <title>can search by billing company name</title>
            <labels/>
            <parameters/>
            <steps/>
            <attachments/>
        </test-case>
        <test-case start='1654056730839' status='passed' stop='1654056730915'>
            <name>can search by billing address 2</name>
            <title>can search by billing address 2</title>
            <labels/>
            <parameters/>
            <steps/>
            <attachments/>
        </test-case>
        <test-case start='1654056730915' status='passed' stop='1654056730989'>
            <name>can search by billing city name</name>
            <title>can search by billing city name</title>
            <labels/>
            <parameters/>
            <steps/>
            <attachments/>
        </test-case>
        <test-case start='1654056730989' status='passed' stop='1654056731063'>
            <name>can search by billing post code</name>
            <title>can search by billing post code</title>
            <labels/>
            <parameters/>
            <steps/>
            <attachments/>
        </test-case>
        <test-case start='1654056731064' status='passed' stop='1654056731168'>
            <name>can search by billing phone</name>
            <title>can search by billing phone</title>
            <labels/>
            <parameters/>
            <steps/>
            <attachments/>
        </test-case>
        <test-case start='1654056731168' status='passed' stop='1654056731245'>
            <name>can search by billing state</name>
            <title>can search by billing state</title>
            <labels/>
            <parameters/>
            <steps/>
            <attachments/>
        </test-case>
        <test-case start='1654056731245' status='passed' stop='1654056731319'>
            <name>can search by shipping first name</name>
            <title>can search by shipping first name</title>
            <labels/>
            <parameters/>
            <steps/>
            <attachments/>
        </test-case>
        <test-case start='1654056731319' status='passed' stop='1654056731396'>
            <name>can search by shipping last name</name>
            <title>can search by shipping last name</title>
            <labels/>
            <parameters/>
            <steps/>
            <attachments/>
        </test-case>
        <test-case start='1654056731396' status='passed' stop='1654056731471'>
            <name>can search by shipping address 2</name>
            <title>can search by shipping address 2</title>
            <labels/>
            <parameters/>
            <steps/>
            <attachments/>
        </test-case>
        <test-case start='1654056731472' status='passed' stop='1654056731547'>
            <name>can search by shipping city</name>
            <title>can search by shipping city</title>
            <labels/>
            <parameters/>
            <steps/>
            <attachments/>
        </test-case>
        <test-case start='1654056731548' status='passed' stop='1654056731624'>
            <name>can search by shipping post code</name>
            <title>can search by shipping post code</title>
            <labels/>
            <parameters/>
            <steps/>
            <attachments/>
        </test-case>
        <test-case start='1654056731624' status='passed' stop='1654056731697'>
            <name>can search by shipping state</name>
            <title>can search by shipping state</title>
            <labels/>
            <parameters/>
            <steps/>
            <attachments/>
        </test-case>
        <test-case start='1654056731698' status='passed' stop='1654056731769'>
            <name>can return an empty result set when no matches were found</name>
            <title>can return an empty result set when no matches were found</title>
            <labels/>
            <parameters/>
            <steps/>
            <attachments/>
        </test-case>
    </test-cases>
</ns2:test-suite>