<?xml version='1.0'?>
<ns2:test-suite xmlns:ns2='urn:model.allure.qatools.yandex.ru' start='1654654493621' stop='1654654496091'>
    <name>Products API tests: CRUD</name>
    <title>Products API tests: CRUD</title>
    <test-cases>
        <test-case start='1654654493622' status='passed' stop='1654654493848'>
            <name>can add a simple product</name>
            <title>can add a simple product</title>
            <labels/>
            <parameters/>
            <steps/>
            <attachments/>
        </test-case>
        <test-case start='1654654493848' status='passed' stop='1654654494218'>
            <name>can add a virtual product</name>
            <title>can add a virtual product</title>
            <labels/>
            <parameters/>
            <steps/>
            <attachments/>
        </test-case>
        <test-case start='1654654494218' status='passed' stop='1654654494583'>
            <name>can add a variable product</name>
            <title>can add a variable product</title>
            <labels/>
            <parameters/>
            <steps/>
            <attachments/>
        </test-case>
        <test-case start='1654654494583' status='passed' stop='1654654494710'>
            <name>can view a single product</name>
            <title>can view a single product</title>
            <labels/>
            <parameters/>
            <steps/>
            <attachments/>
        </test-case>
        <test-case start='1654654494710' status='passed' stop='1654654494864'>
            <name>can update a single product</name>
            <title>can update a single product</title>
            <labels/>
            <parameters/>
            <steps/>
            <attachments/>
        </test-case>
        <test-case start='1654654494864' status='passed' stop='1654654495150'>
            <name>can delete a product</name>
            <title>can delete a product</title>
            <labels/>
            <parameters/>
            <steps/>
            <attachments/>
        </test-case>
    </test-cases>
</ns2:test-suite>