<?xml version='1.0'?>
<ns2:test-suite xmlns:ns2='urn:model.allure.qatools.yandex.ru' start='1653498398698' stop='1653498399219'>
    <name>Coupons API tests List coupons</name>
    <title>Coupons API tests List coupons</title>
    <test-cases>
        <test-case start='1653498398806' status='passed' stop='1653498398884'>
            <name>can list all coupons by default</name>
            <title>can list all coupons by default</title>
            <labels/>
            <parameters/>
            <steps/>
            <attachments/>
        </test-case>
        <test-case start='1653498398884' status='passed' stop='1653498398964'>
            <name>can limit result set to matching code</name>
            <title>can limit result set to matching code</title>
            <labels/>
            <parameters/>
            <steps/>
            <attachments/>
        </test-case>
        <test-case start='1653498398964' status='passed' stop='1653498399042'>
            <name>can paginate results</name>
            <title>can paginate results</title>
            <labels/>
            <parameters/>
            <steps/>
            <attachments/>
        </test-case>
        <test-case start='1653498399042' status='passed' stop='1653498399126'>
            <name>can limit results to matching string</name>
            <title>can limit results to matching string</title>
            <labels/>
            <parameters/>
            <steps/>
            <attachments/>
        </test-case>
    </test-cases>
</ns2:test-suite>