<?xml version='1.0'?>
<ns2:test-suite xmlns:ns2='urn:model.allure.qatools.yandex.ru' start='1652977837092' stop='1652977838977'>
    <name>Products API tests: List All Products List all products orderby</name>
    <title>Products API tests: List All Products List all products orderby</title>
    <test-cases>
        <test-case start='1652977837092' status='passed' stop='1652977837241'>
            <name>default</name>
            <title>default</title>
            <labels/>
            <parameters/>
            <steps/>
            <attachments/>
        </test-case>
        <test-case start='1652977837241' status='passed' stop='1652977837380'>
            <name>date</name>
            <title>date</title>
            <labels/>
            <parameters/>
            <steps/>
            <attachments/>
        </test-case>
        <test-case start='1652977837380' status='passed' stop='1652977837628'>
            <name>id</name>
            <title>id</title>
            <labels/>
            <parameters/>
            <steps/>
            <attachments/>
        </test-case>
        <test-case start='1652977837628' status='passed' stop='1652977837940'>
            <name>title</name>
            <title>title</title>
            <labels/>
            <parameters/>
            <steps/>
            <attachments/>
        </test-case>
        <test-case start='1652977837940' status='passed' stop='1652977838251'>
            <name>slug</name>
            <title>slug</title>
            <labels/>
            <parameters/>
            <steps/>
            <attachments/>
        </test-case>
        <test-case start='1652977838251' status='passed' stop='1652977838556'>
            <name>price</name>
            <title>price</title>
            <labels/>
            <parameters/>
            <steps/>
            <attachments/>
        </test-case>
        <test-case start='1652977838556' status='passed' stop='1652977838784'>
            <name>include</name>
            <title>include</title>
            <labels/>
            <parameters/>
            <steps/>
            <attachments/>
        </test-case>
        <test-case start='1652977838785' status='passed' stop='1652977838879'>
            <name>rating (desc)</name>
            <title>rating (desc)</title>
            <labels/>
            <parameters/>
            <steps/>
            <attachments/>
        </test-case>
        <test-case start='1652977838879' status='pending' stop='1652977838879'>
            <name>rating (asc)</name>
            <title>rating (asc)</title>
            <labels/>
            <parameters/>
            <steps/>
            <attachments/>
            <failure>
                <message>Temporarily disabled with xit</message>
                <stack-trace>undefined</stack-trace>
            </failure>
        </test-case>
        <test-case start='1652977838879' status='passed' stop='1652977838977'>
            <name>popularity (desc)</name>
            <title>popularity (desc)</title>
            <labels/>
            <parameters/>
            <steps/>
            <attachments/>
        </test-case>
        <test-case start='1652977838977' status='pending' stop='1652977838977'>
            <name>popularity (asc)</name>
            <title>popularity (asc)</title>
            <labels/>
            <parameters/>
            <steps/>
            <attachments/>
            <failure>
                <message>Temporarily disabled with xit</message>
                <stack-trace>undefined</stack-trace>
            </failure>
        </test-case>
    </test-cases>
</ns2:test-suite>