<?xml version='1.0'?>
<ns2:test-suite xmlns:ns2='urn:model.allure.qatools.yandex.ru' start='1652977849807' stop='1652977854014'>
    <name>Orders API tests List all orders</name>
    <title>Orders API tests List all orders</title>
    <test-cases>
        <test-case start='1652977849807' status='passed' stop='1652977850483'>
            <name>pagination</name>
            <title>pagination</title>
            <labels/>
            <parameters/>
            <steps/>
            <attachments/>
        </test-case>
        <test-case start='1652977850483' status='passed' stop='1652977850990'>
            <name>inclusion / exclusion</name>
            <title>inclusion / exclusion</title>
            <labels/>
            <parameters/>
            <steps/>
            <attachments/>
        </test-case>
        <test-case start='1652977850990' status='passed' stop='1652977851315'>
            <name>parent</name>
            <title>parent</title>
            <labels/>
            <parameters/>
            <steps/>
            <attachments/>
        </test-case>
        <test-case start='1652977851315' status='passed' stop='1652977851609'>
            <name>status</name>
            <title>status</title>
            <labels/>
            <parameters/>
            <steps/>
            <attachments/>
        </test-case>
        <test-case start='1652977851609' status='passed' stop='1652977851895'>
            <name>customer</name>
            <title>customer</title>
            <labels/>
            <parameters/>
            <steps/>
            <attachments/>
        </test-case>
        <test-case start='1652977851895' status='passed' stop='1652977852009'>
            <name>product</name>
            <title>product</title>
            <labels/>
            <parameters/>
            <steps/>
            <attachments/>
        </test-case>
        <test-case start='1652977852009' status='passed' stop='1652977852346'>
            <name>dp (precision)</name>
            <title>dp (precision)</title>
            <labels/>
            <parameters/>
            <steps/>
            <attachments/>
        </test-case>
        <test-case start='1652977852347' status='passed' stop='1652977852960'>
            <name>search</name>
            <title>search</title>
            <labels/>
            <parameters/>
            <steps/>
            <attachments/>
        </test-case>
    </test-cases>
</ns2:test-suite>