<?xml version='1.0'?>
<ns2:test-suite xmlns:ns2='urn:model.allure.qatools.yandex.ru' start='1654622333482' stop='1654622334134'>
    <name>Products API tests: CRUD Batch update products</name>
    <title>Products API tests: CRUD Batch update products</title>
    <test-cases>
        <test-case start='1654622333482' status='passed' stop='1654622333664'>
            <name>can batch create products</name>
            <title>can batch create products</title>
            <labels/>
            <parameters/>
            <steps/>
            <attachments/>
        </test-case>
        <test-case start='1654622333664' status='passed' stop='1654622333804'>
            <name>can batch update products</name>
            <title>can batch update products</title>
            <labels/>
            <parameters/>
            <steps/>
            <attachments/>
        </test-case>
        <test-case start='1654622333805' status='passed' stop='1654622334133'>
            <name>can batch delete products</name>
            <title>can batch delete products</title>
            <labels/>
            <parameters/>
            <steps/>
            <attachments/>
        </test-case>
    </test-cases>
</ns2:test-suite>