<?xml version='1.0'?>
<ns2:test-suite xmlns:ns2='urn:model.allure.qatools.yandex.ru' start='1653521617669' stop='1653521621618'>
    <name>Orders API tests List all orders</name>
    <title>Orders API tests List all orders</title>
    <test-cases>
        <test-case start='1653521617669' status='passed' stop='1653521618272'>
            <name>pagination</name>
            <title>pagination</title>
            <labels/>
            <parameters/>
            <steps/>
            <attachments/>
        </test-case>
        <test-case start='1653521618272' status='passed' stop='1653521618779'>
            <name>inclusion / exclusion</name>
            <title>inclusion / exclusion</title>
            <labels/>
            <parameters/>
            <steps/>
            <attachments/>
        </test-case>
        <test-case start='1653521618780' status='passed' stop='1653521619091'>
            <name>parent</name>
            <title>parent</title>
            <labels/>
            <parameters/>
            <steps/>
            <attachments/>
        </test-case>
        <test-case start='1653521619091' status='passed' stop='1653521619366'>
            <name>status</name>
            <title>status</title>
            <labels/>
            <parameters/>
            <steps/>
            <attachments/>
        </test-case>
        <test-case start='1653521619366' status='passed' stop='1653521619641'>
            <name>customer</name>
            <title>customer</title>
            <labels/>
            <parameters/>
            <steps/>
            <attachments/>
        </test-case>
        <test-case start='1653521619642' status='passed' stop='1653521619755'>
            <name>product</name>
            <title>product</title>
            <labels/>
            <parameters/>
            <steps/>
            <attachments/>
        </test-case>
        <test-case start='1653521619755' status='passed' stop='1653521620081'>
            <name>dp (precision)</name>
            <title>dp (precision)</title>
            <labels/>
            <parameters/>
            <steps/>
            <attachments/>
        </test-case>
        <test-case start='1653521620081' status='passed' stop='1653521620621'>
            <name>search</name>
            <title>search</title>
            <labels/>
            <parameters/>
            <steps/>
            <attachments/>
        </test-case>
    </test-cases>
</ns2:test-suite>