<?xml version='1.0'?>
<ns2:test-suite xmlns:ns2='urn:model.allure.qatools.yandex.ru' start='1653015861155' stop='1653015863439'>
    <name>Products API tests: CRUD</name>
    <title>Products API tests: CRUD</title>
    <test-cases>
        <test-case start='1653015861156' status='passed' stop='1653015861377'>
            <name>can add a simple product</name>
            <title>can add a simple product</title>
            <labels/>
            <parameters/>
            <steps/>
            <attachments/>
        </test-case>
        <test-case start='1653015861377' status='passed' stop='1653015861707'>
            <name>can add a virtual product</name>
            <title>can add a virtual product</title>
            <labels/>
            <parameters/>
            <steps/>
            <attachments/>
        </test-case>
        <test-case start='1653015861707' status='passed' stop='1653015862069'>
            <name>can add a variable product</name>
            <title>can add a variable product</title>
            <labels/>
            <parameters/>
            <steps/>
            <attachments/>
        </test-case>
        <test-case start='1653015862069' status='passed' stop='1653015862185'>
            <name>can view a single product</name>
            <title>can view a single product</title>
            <labels/>
            <parameters/>
            <steps/>
            <attachments/>
        </test-case>
        <test-case start='1653015862185' status='passed' stop='1653015862324'>
            <name>can update a single product</name>
            <title>can update a single product</title>
            <labels/>
            <parameters/>
            <steps/>
            <attachments/>
        </test-case>
        <test-case start='1653015862324' status='passed' stop='1653015862579'>
            <name>can delete a product</name>
            <title>can delete a product</title>
            <labels/>
            <parameters/>
            <steps/>
            <attachments/>
        </test-case>
    </test-cases>
</ns2:test-suite>