<?xml version='1.0'?>
<ns2:test-suite xmlns:ns2='urn:model.allure.qatools.yandex.ru' start='1653031321917' stop='1653031328832'>
    <name>Products API tests: List All Products List all products</name>
    <title>Products API tests: List All Products List all products</title>
    <test-cases>
        <test-case start='1653031321918' status='passed' stop='1653031322100'>
            <name>defaults</name>
            <title>defaults</title>
            <labels/>
            <parameters/>
            <steps/>
            <attachments/>
        </test-case>
        <test-case start='1653031322100' status='passed' stop='1653031322681'>
            <name>pagination</name>
            <title>pagination</title>
            <labels/>
            <parameters/>
            <steps/>
            <attachments/>
        </test-case>
        <test-case start='1653031322681' status='passed' stop='1653031322901'>
            <name>search</name>
            <title>search</title>
            <labels/>
            <parameters/>
            <steps/>
            <attachments/>
        </test-case>
        <test-case start='1653031322901' status='passed' stop='1653031323410'>
            <name>inclusion / exclusion</name>
            <title>inclusion / exclusion</title>
            <labels/>
            <parameters/>
            <steps/>
            <attachments/>
        </test-case>
        <test-case start='1653031323410' status='passed' stop='1653031323607'>
            <name>slug</name>
            <title>slug</title>
            <labels/>
            <parameters/>
            <steps/>
            <attachments/>
        </test-case>
        <test-case start='1653031323607' status='passed' stop='1653031323801'>
            <name>sku</name>
            <title>sku</title>
            <labels/>
            <parameters/>
            <steps/>
            <attachments/>
        </test-case>
        <test-case start='1653031323801' status='passed' stop='1653031324280'>
            <name>type</name>
            <title>type</title>
            <labels/>
            <parameters/>
            <steps/>
            <attachments/>
        </test-case>
        <test-case start='1653031324281' status='passed' stop='1653031324543'>
            <name>featured</name>
            <title>featured</title>
            <labels/>
            <parameters/>
            <steps/>
            <attachments/>
        </test-case>
        <test-case start='1653031324543' status='passed' stop='1653031324816'>
            <name>categories</name>
            <title>categories</title>
            <labels/>
            <parameters/>
            <steps/>
            <attachments/>
        </test-case>
        <test-case start='1653031324816' status='passed' stop='1653031325095'>
            <name>on sale</name>
            <title>on sale</title>
            <labels/>
            <parameters/>
            <steps/>
            <attachments/>
        </test-case>
        <test-case start='1653031325095' status='passed' stop='1653031325469'>
            <name>price</name>
            <title>price</title>
            <labels/>
            <parameters/>
            <steps/>
            <attachments/>
        </test-case>
        <test-case start='1653031325469' status='passed' stop='1653031325689'>
            <name>before / after</name>
            <title>before / after</title>
            <labels/>
            <parameters/>
            <steps/>
            <attachments/>
        </test-case>
        <test-case start='1653031325689' status='passed' stop='1653031325804'>
            <name>attributes</name>
            <title>attributes</title>
            <labels/>
            <parameters/>
            <steps/>
            <attachments/>
        </test-case>
        <test-case start='1653031325804' status='passed' stop='1653031326001'>
            <name>status</name>
            <title>status</title>
            <labels/>
            <parameters/>
            <steps/>
            <attachments/>
        </test-case>
        <test-case start='1653031326001' status='passed' stop='1653031326104'>
            <name>shipping class</name>
            <title>shipping class</title>
            <labels/>
            <parameters/>
            <steps/>
            <attachments/>
        </test-case>
        <test-case start='1653031326104' status='passed' stop='1653031326206'>
            <name>tax class</name>
            <title>tax class</title>
            <labels/>
            <parameters/>
            <steps/>
            <attachments/>
        </test-case>
        <test-case start='1653031326206' status='passed' stop='1653031326306'>
            <name>stock status</name>
            <title>stock status</title>
            <labels/>
            <parameters/>
            <steps/>
            <attachments/>
        </test-case>
        <test-case start='1653031326306' status='passed' stop='1653031326419'>
            <name>tags</name>
            <title>tags</title>
            <labels/>
            <parameters/>
            <steps/>
            <attachments/>
        </test-case>
        <test-case start='1653031326419' status='passed' stop='1653031326689'>
            <name>parent</name>
            <title>parent</title>
            <labels/>
            <parameters/>
            <steps/>
            <attachments/>
        </test-case>
    </test-cases>
</ns2:test-suite>