<?xml version='1.0'?>
<ns2:test-suite xmlns:ns2='urn:model.allure.qatools.yandex.ru' start='1655225853707' stop='1655225854708'>
    <name>Orders API tests List all orders orderby</name>
    <title>Orders API tests List all orders orderby</title>
    <test-cases>
        <test-case start='1655225853707' status='passed' stop='1655225853893'>
            <name>default</name>
            <title>default</title>
            <labels/>
            <parameters/>
            <steps/>
            <attachments/>
        </test-case>
        <test-case start='1655225853893' status='passed' stop='1655225854082'>
            <name>date</name>
            <title>date</title>
            <labels/>
            <parameters/>
            <steps/>
            <attachments/>
        </test-case>
        <test-case start='1655225854082' status='passed' stop='1655225854451'>
            <name>id</name>
            <title>id</title>
            <labels/>
            <parameters/>
            <steps/>
            <attachments/>
        </test-case>
        <test-case start='1655225854451' status='passed' stop='1655225854708'>
            <name>include</name>
            <title>include</title>
            <labels/>
            <parameters/>
            <steps/>
            <attachments/>
        </test-case>
    </test-cases>
</ns2:test-suite>